{"frames": [

{
	"filename": "FROG_Drop_00.png",
	"frame": {"x":180,"y":211,"w":78,"h":207},
	"rotated": false,
	"trimmed": true,
	"spriteSourceSize": {"x":111,"y":65,"w":78,"h":207},
	"sourceSize": {"w":300,"h":300}
},
{
	"filename": "FROG_Drop_02.png",
	"frame": {"x":168,"y":1,"w":78,"h":208},
	"rotated": false,
	"trimmed": true,
	"spriteSourceSize": {"x":111,"y":64,"w":78,"h":208},
	"sourceSize": {"w":300,"h":300}
},
{
	"filename": "FROG_Drop_04.png",
	"frame": {"x":86,"y":1,"w":80,"h":212},
	"rotated": false,
	"trimmed": true,
	"spriteSourceSize": {"x":110,"y":60,"w":80,"h":212},
	"sourceSize": {"w":300,"h":300}
},
{
	"filename": "FROG_Drop_06.png",
	"frame": {"x":1,"y":1,"w":83,"h":214},
	"rotated": false,
	"trimmed": true,
	"spriteSourceSize": {"x":108,"y":58,"w":83,"h":214},
	"sourceSize": {"w":300,"h":300}
},
{
	"filename": "FROG_Drop_08.png",
	"frame": {"x":1,"y":217,"w":86,"h":213},
	"rotated": false,
	"trimmed": true,
	"spriteSourceSize": {"x":107,"y":59,"w":86,"h":213},
	"sourceSize": {"w":300,"h":300}
},
{
	"filename": "FROG_Drop_10.png",
	"frame": {"x":89,"y":215,"w":89,"h":210},
	"rotated": false,
	"trimmed": true,
	"spriteSourceSize": {"x":106,"y":62,"w":89,"h":210},
	"sourceSize": {"w":300,"h":300}
},
{
	"filename": "FROG_Drop_12.png",
	"frame": {"x":260,"y":208,"w":95,"h":201},
	"rotated": false,
	"trimmed": true,
	"spriteSourceSize": {"x":105,"y":71,"w":95,"h":201},
	"sourceSize": {"w":300,"h":300}
},
{
	"filename": "FROG_Drop_14.png",
	"frame": {"x":408,"y":1,"w":86,"h":181},
	"rotated": false,
	"trimmed": true,
	"spriteSourceSize": {"x":102,"y":91,"w":86,"h":181},
	"sourceSize": {"w":300,"h":300}
},
{
	"filename": "FROG_Drop_16.png",
	"frame": {"x":768,"y":360,"w":107,"h":150},
	"rotated": false,
	"trimmed": true,
	"spriteSourceSize": {"x":95,"y":122,"w":107,"h":150},
	"sourceSize": {"w":300,"h":300}
},
{
	"filename": "FROG_Drop_18.png",
	"frame": {"x":1069,"y":335,"w":150,"h":151},
	"rotated": false,
	"trimmed": true,
	"spriteSourceSize": {"x":72,"y":124,"w":150,"h":151},
	"sourceSize": {"w":300,"h":300}
},
{
	"filename": "FROG_Drop_20.png",
	"frame": {"x":962,"y":168,"w":188,"h":165},
	"rotated": false,
	"trimmed": true,
	"spriteSourceSize": {"x":52,"y":117,"w":188,"h":165},
	"sourceSize": {"w":300,"h":300}
},
{
	"filename": "FROG_Drop_22.png",
	"frame": {"x":654,"y":182,"w":207,"h":176},
	"rotated": false,
	"trimmed": true,
	"spriteSourceSize": {"x":42,"y":113,"w":207,"h":176},
	"sourceSize": {"w":300,"h":300}
},
{
	"filename": "FROG_Drop_24.png",
	"frame": {"x":441,"y":184,"w":211,"h":180},
	"rotated": false,
	"trimmed": true,
	"spriteSourceSize": {"x":40,"y":112,"w":211,"h":180},
	"sourceSize": {"w":300,"h":300}
},
{
	"filename": "FROG_Drop_26.png",
	"frame": {"x":496,"y":1,"w":211,"h":179},
	"rotated": false,
	"trimmed": true,
	"spriteSourceSize": {"x":40,"y":112,"w":211,"h":179},
	"sourceSize": {"w":300,"h":300}
},
{
	"filename": "FROG_Drop_28.png",
	"frame": {"x":709,"y":1,"w":207,"h":174},
	"rotated": false,
	"trimmed": true,
	"spriteSourceSize": {"x":42,"y":116,"w":207,"h":174},
	"sourceSize": {"w":300,"h":300}
},
{
	"filename": "FROG_Drop_30.png",
	"frame": {"x":918,"y":1,"w":201,"h":165},
	"rotated": false,
	"trimmed": true,
	"spriteSourceSize": {"x":45,"y":121,"w":201,"h":165},
	"sourceSize": {"w":300,"h":300}
},
{
	"filename": "FROG_Drop_32.png",
	"frame": {"x":877,"y":348,"w":190,"h":151},
	"rotated": false,
	"trimmed": true,
	"spriteSourceSize": {"x":51,"y":130,"w":190,"h":151},
	"sourceSize": {"w":300,"h":300}
},
{
	"filename": "FROG_Drop_34.png",
	"frame": {"x":593,"y":366,"w":173,"h":136},
	"rotated": false,
	"trimmed": true,
	"spriteSourceSize": {"x":60,"y":140,"w":173,"h":136},
	"sourceSize": {"w":300,"h":300}
},
{
	"filename": "FROG_Drop_36.png",
	"frame": {"x":441,"y":366,"w":150,"h":138},
	"rotated": false,
	"trimmed": true,
	"spriteSourceSize": {"x":72,"y":134,"w":150,"h":138},
	"sourceSize": {"w":300,"h":300}
},
{
	"filename": "FROG_Drop_38.png",
	"frame": {"x":1121,"y":1,"w":118,"h":151},
	"rotated": false,
	"trimmed": true,
	"spriteSourceSize": {"x":89,"y":121,"w":118,"h":151},
	"sourceSize": {"w":300,"h":300}
},
{
	"filename": "FROG_Drop_40.png",
	"frame": {"x":863,"y":177,"w":97,"h":169},
	"rotated": false,
	"trimmed": true,
	"spriteSourceSize": {"x":97,"y":103,"w":97,"h":169},
	"sourceSize": {"w":300,"h":300}
},
{
	"filename": "FROG_Drop_42.png",
	"frame": {"x":357,"y":204,"w":82,"h":188},
	"rotated": false,
	"trimmed": true,
	"spriteSourceSize": {"x":103,"y":84,"w":82,"h":188},
	"sourceSize": {"w":300,"h":300}
},
{
	"filename": "FROG_Drop_44.png",
	"frame": {"x":328,"y":1,"w":78,"h":201},
	"rotated": false,
	"trimmed": true,
	"spriteSourceSize": {"x":109,"y":71,"w":78,"h":201},
	"sourceSize": {"w":300,"h":300}
},
{
	"filename": "FROG_Drop_46.png",
	"frame": {"x":248,"y":1,"w":78,"h":205},
	"rotated": false,
	"trimmed": true,
	"spriteSourceSize": {"x":110,"y":67,"w":78,"h":205},
	"sourceSize": {"w":300,"h":300}
}],
"meta": {
	"app": "https://www.codeandweb.com/texturepacker",
	"version": "1.0",
	"image": "FROG_Drop.png",
	"format": "RGBA8888",
	"size": {"w":1240,"h":511},
	"scale": "1",
	"smartupdate": "$TexturePacker:SmartUpdate:8930441e75c5754d4534fae3aef2a905:00f03847a22c7bd94dc8d44ca99f69e5:e65aa5d3c18702abc5f6d1dd68df6c89$"
}
}
