{"frames": [

{
	"filename": "PINEAPPLE_XArmsSide_00.png",
	"frame": {"x":125,"y":1,"w":121,"h":253},
	"rotated": false,
	"trimmed": true,
	"spriteSourceSize": {"x":118,"y":19,"w":121,"h":253},
	"sourceSize": {"w":300,"h":300}
},
{
	"filename": "PINEAPPLE_XArmsSide_02.png",
	"frame": {"x":248,"y":1,"w":121,"h":253},
	"rotated": false,
	"trimmed": true,
	"spriteSourceSize": {"x":118,"y":19,"w":121,"h":253},
	"sourceSize": {"w":300,"h":300}
},
{
	"filename": "PINEAPPLE_XArmsSide_04.png",
	"frame": {"x":371,"y":1,"w":121,"h":253},
	"rotated": false,
	"trimmed": true,
	"spriteSourceSize": {"x":118,"y":19,"w":121,"h":253},
	"sourceSize": {"w":300,"h":300}
},
{
	"filename": "PINEAPPLE_XArmsSide_06.png",
	"frame": {"x":494,"y":1,"w":121,"h":253},
	"rotated": false,
	"trimmed": true,
	"spriteSourceSize": {"x":119,"y":19,"w":121,"h":253},
	"sourceSize": {"w":300,"h":300}
},
{
	"filename": "PINEAPPLE_XArmsSide_08.png",
	"frame": {"x":1,"y":1,"w":122,"h":253},
	"rotated": false,
	"trimmed": true,
	"spriteSourceSize": {"x":119,"y":19,"w":122,"h":253},
	"sourceSize": {"w":300,"h":300}
},
{
	"filename": "PINEAPPLE_XArmsSide_10.png",
	"frame": {"x":780,"y":1,"w":120,"h":252},
	"rotated": false,
	"trimmed": true,
	"spriteSourceSize": {"x":119,"y":20,"w":120,"h":252},
	"sourceSize": {"w":300,"h":300}
},
{
	"filename": "PINEAPPLE_XArmsSide_12.png",
	"frame": {"x":902,"y":1,"w":113,"h":252},
	"rotated": false,
	"trimmed": true,
	"spriteSourceSize": {"x":119,"y":20,"w":113,"h":252},
	"sourceSize": {"w":300,"h":300}
},
{
	"filename": "PINEAPPLE_XArmsSide_14.png",
	"frame": {"x":1017,"y":1,"w":100,"h":252},
	"rotated": false,
	"trimmed": true,
	"spriteSourceSize": {"x":119,"y":20,"w":100,"h":252},
	"sourceSize": {"w":300,"h":300}
},
{
	"filename": "PINEAPPLE_XArmsSide_16.png",
	"frame": {"x":1119,"y":1,"w":87,"h":252},
	"rotated": false,
	"trimmed": true,
	"spriteSourceSize": {"x":119,"y":20,"w":87,"h":252},
	"sourceSize": {"w":300,"h":300}
},
{
	"filename": "PINEAPPLE_XArmsSide_18.png",
	"frame": {"x":1208,"y":1,"w":82,"h":252},
	"rotated": false,
	"trimmed": true,
	"spriteSourceSize": {"x":115,"y":20,"w":82,"h":252},
	"sourceSize": {"w":300,"h":300}
},
{
	"filename": "PINEAPPLE_XArmsSide_20.png",
	"frame": {"x":617,"y":1,"w":80,"h":253},
	"rotated": false,
	"trimmed": true,
	"spriteSourceSize": {"x":112,"y":19,"w":80,"h":253},
	"sourceSize": {"w":300,"h":300}
},
{
	"filename": "PINEAPPLE_XArmsSide_22.png",
	"frame": {"x":699,"y":1,"w":79,"h":253},
	"rotated": false,
	"trimmed": true,
	"spriteSourceSize": {"x":111,"y":19,"w":79,"h":253},
	"sourceSize": {"w":300,"h":300}
}],
"meta": {
	"app": "https://www.codeandweb.com/texturepacker",
	"version": "1.0",
	"image": "PINEAPPLE_XArmsSide.png",
	"format": "RGBA8888",
	"size": {"w":1291,"h":255},
	"scale": "1",
	"smartupdate": "$TexturePacker:SmartUpdate:db73e9336b570e0ea219e2390a92846e:2bd9b31ff20f1f48e7bb180bf5e8c565:73cfbea474e1859086652288cb860e57$"
}
}
